mnmt/__init__.py
mnmt/alternating_character_table/__init__.py
mnmt/alternating_character_table/act.py
mnmt/alternating_character_table/dict_act.xlsx
mnmt/attention/__init__.py
mnmt/attention/additive_attention.py
mnmt/attention/attention.py
mnmt/datasets/__init__.py
mnmt/datasets/dict_data/__init__.py
mnmt/datasets/dict_data/test.tsv
mnmt/datasets/dict_data/train.tsv
mnmt/datasets/dict_data/valid.tsv
mnmt/datasets/news_data/__init__.py
mnmt/datasets/news_data/test.json
mnmt/datasets/news_data/test.tsv
mnmt/datasets/news_data/train.tsv
mnmt/datasets/news_data/valid.tsv
mnmt/decoder/__init__.py
mnmt/decoder/basic_decoder.py
mnmt/decoder/basic_feed_forward_decoder.py
mnmt/decoder/beam_decoder.py
mnmt/decoder/beam_decoder_batch.py
mnmt/decoder/beam_decoder_old.py
mnmt/decoder/bridge.py
mnmt/decoder/greedy_decoder.py
mnmt/encoder/__init__.py
mnmt/encoder/basic_encoder.py
mnmt/inputter/__init__.py
mnmt/inputter/arguments_feeder.py
mnmt/inputter/batch_generator.py
mnmt/inputter/data_container.py
mnmt/inputter/module_arguments_feeder.py
mnmt/inputter/trainer_arguments_feeder.py
mnmt/model/__init__.py
mnmt/model/basic_seq2seq.py
mnmt/model/multi_task_seq2seq.py
mnmt/trainer/__init__.py
mnmt/trainer/trainer.py
mnmt/trainer/utils.py
mnmt/translator/__init__.py
mnmt/translator/basic_translator.py
mnmt/translator/seq2seq_translator.py
multi_task_nmt_lawhy-0.1.3.dist-info/LICENSE
multi_task_nmt_lawhy-0.1.3.dist-info/METADATA
multi_task_nmt_lawhy-0.1.3.dist-info/WHEEL
multi_task_nmt_lawhy-0.1.3.dist-info/top_level.txt
multi_task_nmt_lawhy-0.1.3.dist-info/RECORD
